trinity/__init__.py
trinity/algorithm/__init__.py
trinity/algorithm/algorithm.py
trinity/algorithm/key_mapper.py
trinity/algorithm/utils.py
trinity/algorithm/advantage_fn/__init__.py
trinity/algorithm/advantage_fn/advantage_fn.py
trinity/algorithm/advantage_fn/asymre_advantage.py
trinity/algorithm/advantage_fn/grpo_advantage.py
trinity/algorithm/advantage_fn/multi_step_grpo_advantage.py
trinity/algorithm/advantage_fn/on_policy_distill_advantage.py
trinity/algorithm/advantage_fn/opmd_advantage.py
trinity/algorithm/advantage_fn/ppo_advantage.py
trinity/algorithm/advantage_fn/rec_advantage.py
trinity/algorithm/advantage_fn/reinforce_advantage.py
trinity/algorithm/advantage_fn/reinforce_plus_plus_advantage.py
trinity/algorithm/advantage_fn/remax_advantage.py
trinity/algorithm/advantage_fn/rloo_advantage.py
trinity/algorithm/entropy_loss_fn/__init__.py
trinity/algorithm/entropy_loss_fn/entropy_loss_fn.py
trinity/algorithm/kl_fn/__init__.py
trinity/algorithm/kl_fn/kl_fn.py
trinity/algorithm/policy_loss_fn/__init__.py
trinity/algorithm/policy_loss_fn/chord_policy_loss.py
trinity/algorithm/policy_loss_fn/cispo_policy_loss.py
trinity/algorithm/policy_loss_fn/dpo_loss.py
trinity/algorithm/policy_loss_fn/gspo_policy_loss.py
trinity/algorithm/policy_loss_fn/importance_sampling_policy_loss.py
trinity/algorithm/policy_loss_fn/mix_policy_loss.py
trinity/algorithm/policy_loss_fn/opmd_policy_loss.py
trinity/algorithm/policy_loss_fn/policy_loss_fn.py
trinity/algorithm/policy_loss_fn/ppo_policy_loss.py
trinity/algorithm/policy_loss_fn/rec_policy_loss.py
trinity/algorithm/policy_loss_fn/sapo_policy_loss.py
trinity/algorithm/policy_loss_fn/sft_loss.py
trinity/algorithm/policy_loss_fn/sppo_loss_fn.py
trinity/algorithm/policy_loss_fn/topr_policy_loss.py
trinity/algorithm/sample_strategy/__init__.py
trinity/algorithm/sample_strategy/mix_sample_strategy.py
trinity/algorithm/sample_strategy/sample_strategy.py
trinity/algorithm/sample_strategy/utils.py
trinity/buffer/__init__.py
trinity_rft-0.4.1.dist-info/licenses/LICENSE
trinity_rft-0.4.1.dist-info/METADATA
trinity_rft-0.4.1.dist-info/WHEEL
trinity_rft-0.4.1.dist-info/entry_points.txt
trinity_rft-0.4.1.dist-info/top_level.txt
trinity_rft-0.4.1.dist-info/RECORD
