Metadata-Version: 2.4
Name: trinity-rft
Version: 0.4.1
Summary: Trinity-RFT: A Framework for Training Large Language Models with Reinforcement Fine-Tuning
Author-email: Trinity-RFT Team <trinity-rft@outlook.com>
Project-URL: Homepage, https://github.com/modelscope/Trinity-RFT
Project-URL: Documentation, https://modelscope.github.io/Trinity-RFT/
Classifier: Development Status :: 3 - Alpha
Classifier: Intended Audience :: Developers
Classifier: License :: OSI Approved :: Apache Software License
Classifier: Programming Language :: Python :: 3 :: Only
Classifier: Programming Language :: Python :: 3.10
Classifier: Programming Language :: Python :: 3.11
Classifier: Programming Language :: Python :: 3.12
Requires-Python: <3.13,>=3.10
License-File: LICENSE
Requires-Dist: verl==0.7.0
Requires-Dist: ray[default]>=2.50.0
Requires-Dist: tensordict
Requires-Dist: wandb
Requires-Dist: omegaconf
Requires-Dist: sqlalchemy
Requires-Dist: psycopg2-binary
Requires-Dist: networkx
Requires-Dist: latex2sympy2_extended
Requires-Dist: math_verify>=0.8.0
Requires-Dist: ninja
Requires-Dist: fire
Requires-Dist: streamlit
Requires-Dist: flask
Requires-Dist: requests
Requires-Dist: tensorboard
Requires-Dist: openai
Requires-Dist: jsonlines
Requires-Dist: sortedcontainers
Requires-Dist: word2number
Requires-Dist: transformers
Requires-Dist: datasets
Provides-Extra: vllm
Requires-Dist: vllm<=0.11.0,>=0.10.2; extra == "vllm"
Provides-Extra: data
Requires-Dist: py-data-juicer>=1.4.3; extra == "data"
Provides-Extra: agent
Requires-Dist: agentscope>=1.0.9; extra == "agent"
Provides-Extra: rm-gallery
Requires-Dist: rm-gallery>=0.1.5; extra == "rm-gallery"
Provides-Extra: dev
Requires-Dist: pre-commit>=2.17.0; extra == "dev"
Requires-Dist: black>=23.7.0; extra == "dev"
Requires-Dist: flake8>=6.1.0; extra == "dev"
Requires-Dist: flake8-docstrings>=1.6.0; extra == "dev"
Requires-Dist: isort>=5.12.0; extra == "dev"
Requires-Dist: mypy>=1.7.0; extra == "dev"
Requires-Dist: pytest>=8.0.0; extra == "dev"
Requires-Dist: pytest-json-ctrf; extra == "dev"
Requires-Dist: parameterized; extra == "dev"
Requires-Dist: matplotlib; extra == "dev"
Requires-Dist: viztracer; extra == "dev"
Provides-Extra: megatron
Requires-Dist: megatron-core[mlm]==0.13.1; extra == "megatron"
Provides-Extra: tinker
Requires-Dist: tinker; python_version >= "3.11" and extra == "tinker"
Provides-Extra: doc
Requires-Dist: sphinx<9.0.0; extra == "doc"
Requires-Dist: sphinx-autobuild; extra == "doc"
Requires-Dist: sphinx-book-theme; extra == "doc"
Requires-Dist: myst-parser; extra == "doc"
Requires-Dist: sphinxcontrib-apidoc; extra == "doc"
Requires-Dist: sphinx-multiversion; extra == "doc"
Requires-Dist: sphinxcontrib-mermaid; extra == "doc"
Provides-Extra: mm
Requires-Dist: qwen-vl-utils; extra == "mm"
Provides-Extra: flash-attn
Requires-Dist: flash-attn==2.8.1; extra == "flash-attn"
Dynamic: license-file
